Metadata-Version: 2.1
Name: solstice
Version: 0.0.28
Summary: Core implementation for ArtellaPipe based Solstice Pipeline
Home-page: https://github.com/Solstice-Short-Film/solstice
Author: Tomas Poveda
Author-email: tpovedatd@gmail.com
License: MIT
Platform: UNKNOWN
Provides-Extra: dev
Provides-Extra: test
